py_node_manager/__init__.py
py_node_manager/logger.py
py_node_manager/manager.py
py_node_manager-0.1.2.dist-info/licenses/LICENSE
py_node_manager-0.1.2.dist-info/METADATA
py_node_manager-0.1.2.dist-info/WHEEL
py_node_manager-0.1.2.dist-info/top_level.txt
py_node_manager-0.1.2.dist-info/RECORD
