Metadata-Version: 2.4
Name: py-node-manager
Version: 0.1.2
Summary: A tool library for conveniently using Node.js in Python
Author-email: insistence <3055204202@qq.com>
Project-URL: Homepage, https://github.com/HogaStack/py-node-manager
Project-URL: Documentation, https://github.com/HogaStack/py-node-manager
Project-URL: Repository, https://github.com/HogaStack/py-node-manager
Project-URL: Issues, https://github.com/HogaStack/py-node-manager/issues
Classifier: Development Status :: 5 - Production/Stable
Classifier: Intended Audience :: Developers
Classifier: License :: OSI Approved :: MIT License
Classifier: Operating System :: OS Independent
Classifier: Programming Language :: Python :: 3
Classifier: Programming Language :: Python :: 3.8
Classifier: Programming Language :: Python :: 3.9
Classifier: Programming Language :: Python :: 3.10
Classifier: Programming Language :: Python :: 3.11
Classifier: Programming Language :: Python :: 3.12
Requires-Python: >=3.8
License-File: LICENSE
Provides-Extra: dev
Requires-Dist: build; extra == "dev"
Requires-Dist: pytest>=6.0.0; extra == "dev"
Requires-Dist: pytest-cov>=2.10.0; extra == "dev"
Requires-Dist: twine; extra == "dev"
Dynamic: license-file
